{
    "Category": 1.0,
    "pslist.nproc": 93.0,
    "pslist.nppid": 18.0,
    "pslist.avg_threads": 4.430107527,
    "pslist.nprocs64bit": 0.0,
    "pslist.avg_handlers": 97.2688172,
    "dlllist.ndlls": 1751.0,
    "dlllist.avg_dlls_per_proc": 18.82795699,
    "handles.nhandles": 9095.0,
    "handles.avg_handles_per_proc": 206.7045455,
    "handles.nport": 0.0,
    "handles.nfile": 865.0,
    "handles.nevent": 3085.0,
    "handles.ndesktop": 47.0,
    "handles.nkey": 720.0,
    "handles.nthread": 759.0,
    "handles.ndirectory": 109.0,
    "handles.nsemaphore": 663.0,
    "handles.ntimer": 129.0,
    "handles.nsection": 184.0,
    "handles.nmutant": 276.0,
    "ldrmodules.not_in_load": 49.0,
    "ldrmodules.not_in_init": 92.0,
    "ldrmodules.not_in_mem": 49.0,
    "ldrmodules.not_in_load_avg": 0.028064147,
    "ldrmodules.not_in_init_avg": 0.052691867,
    "ldrmodules.not_in_mem_avg": 0.028064147,
    "malfind.ninjections": 9.0,
    "malfind.commitCharge": 63.0,
    "malfind.protection": 54.0,
    "malfind.uniqueInjections": 2.25,
    "psxview.not_in_pslist": 2.0,
    "psxview.not_in_eprocess_pool": 0.0,
    "psxview.not_in_ethread_pool": 51.0,
    "psxview.not_in_pspcid_list": 2.0,
    "psxview.not_in_csrss_handles": 55.0,
    "psxview.not_in_session": 4.0,
    "psxview.not_in_deskthrd": 57.0,
    "psxview.not_in_pslist_false_avg": 0.021052632,
    "psxview.not_in_eprocess_pool_false_avg": 0.0,
    "psxview.not_in_ethread_pool_false_avg": 0.536842105,
    "psxview.not_in_pspcid_list_false_avg": 0.021052632,
    "psxview.not_in_csrss_handles_false_avg": 0.578947368,
    "psxview.not_in_session_false_avg": 0.042105263,
    "psxview.not_in_deskthrd_false_avg": 0.6,
    "modules.nmodules": 138.0,
    "svcscan.nservices": 389.0,
    "svcscan.kernel_drivers": 221.0,
    "svcscan.fs_drivers": 26.0,
    "svcscan.process_services": 24.0,
    "svcscan.shared_process_services": 116.0,
    "svcscan.interactive_process_services": 0.0,
    "svcscan.nactive": 122.0,
    "callbacks.ncallbacks": 87.0,
    "callbacks.nanonymous": 0.0,
    "callbacks.ngeneric": 8.0,
    "Class": 1.0,
    "sample_id": 36128.0
}