{
    "Category": 0.0,
    "pslist.nproc": 42.0,
    "pslist.nppid": 17.0,
    "pslist.avg_threads": 10.83277782,
    "pslist.nprocs64bit": 0.0,
    "pslist.avg_handlers": 255.1550267,
    "dlllist.ndlls": 1816.0,
    "dlllist.avg_dlls_per_proc": 43.25801614,
    "handles.nhandles": 10717.0,
    "handles.avg_handles_per_proc": 261.4027103,
    "handles.nport": 0.0,
    "handles.nfile": 837.0,
    "handles.nevent": 3731.0,
    "handles.ndesktop": 46.0,
    "handles.nkey": 925.0,
    "handles.nthread": 877.0,
    "handles.ndirectory": 103.0,
    "handles.nsemaphore": 728.0,
    "handles.ntimer": 132.0,
    "handles.nsection": 354.0,
    "handles.nmutant": 343.0,
    "ldrmodules.not_in_load": 75.0,
    "ldrmodules.not_in_init": 114.0,
    "ldrmodules.not_in_mem": 75.0,
    "ldrmodules.not_in_load_avg": 0.040899298,
    "ldrmodules.not_in_init_avg": 0.06209469,
    "ldrmodules.not_in_mem_avg": 0.040899298,
    "malfind.ninjections": 4.0,
    "malfind.commitCharge": 5.0,
    "malfind.protection": 25.0,
    "malfind.uniqueInjections": 1.441852028,
    "psxview.not_in_pslist": 11.0,
    "psxview.not_in_eprocess_pool": 0.0,
    "psxview.not_in_ethread_pool": 12.0,
    "psxview.not_in_pspcid_list": 11.0,
    "psxview.not_in_csrss_handles": 16.0,
    "psxview.not_in_session": 13.0,
    "psxview.not_in_deskthrd": 18.0,
    "psxview.not_in_pslist_false_avg": 0.21744467,
    "psxview.not_in_eprocess_pool_false_avg": 0.0,
    "psxview.not_in_ethread_pool_false_avg": 0.236076939,
    "psxview.not_in_pspcid_list_false_avg": 0.21744467,
    "psxview.not_in_csrss_handles_false_avg": 0.310606018,
    "psxview.not_in_session_false_avg": 0.254709209,
    "psxview.not_in_deskthrd_false_avg": 0.347870558,
    "modules.nmodules": 138.0,
    "svcscan.nservices": 392.0,
    "svcscan.kernel_drivers": 222.0,
    "svcscan.fs_drivers": 26.0,
    "svcscan.process_services": 24.0,
    "svcscan.shared_process_services": 118.0,
    "svcscan.interactive_process_services": 0.0,
    "svcscan.nactive": 126.0,
    "callbacks.ncallbacks": 87.0,
    "callbacks.nanonymous": 0.0,
    "callbacks.ngeneric": 8.0,
    "Class": 0.0,
    "sample_id": 8010.0
}