{
    "Category": 0.0,
    "pslist.nproc": 32.0,
    "pslist.nppid": 11.0,
    "pslist.avg_threads": 12.39737088,
    "pslist.nprocs64bit": 0.0,
    "pslist.avg_handlers": 277.8392352,
    "dlllist.ndlls": 1493.0,
    "dlllist.avg_dlls_per_proc": 46.67812425,
    "handles.nhandles": 8892.0,
    "handles.avg_handles_per_proc": 292.1896033,
    "handles.nport": 0.0,
    "handles.nfile": 691.0,
    "handles.nevent": 3058.0,
    "handles.ndesktop": 33.0,
    "handles.nkey": 723.0,
    "handles.nthread": 759.0,
    "handles.ndirectory": 81.0,
    "handles.nsemaphore": 660.0,
    "handles.ntimer": 121.0,
    "handles.nsection": 229.0,
    "handles.nmutant": 296.0,
    "ldrmodules.not_in_load": 54.0,
    "ldrmodules.not_in_init": 81.0,
    "ldrmodules.not_in_mem": 54.0,
    "ldrmodules.not_in_load_avg": 0.037710795,
    "ldrmodules.not_in_init_avg": 0.056221434,
    "ldrmodules.not_in_mem_avg": 0.037710795,
    "malfind.ninjections": 2.0,
    "malfind.commitCharge": 3.0,
    "malfind.protection": 14.0,
    "malfind.uniqueInjections": 1.780158921,
    "psxview.not_in_pslist": 4.0,
    "psxview.not_in_eprocess_pool": 0.0,
    "psxview.not_in_ethread_pool": 6.0,
    "psxview.not_in_pspcid_list": 4.0,
    "psxview.not_in_csrss_handles": 10.0,
    "psxview.not_in_session": 6.0,
    "psxview.not_in_deskthrd": 12.0,
    "psxview.not_in_pslist_false_avg": 0.126158281,
    "psxview.not_in_eprocess_pool_false_avg": 0.0,
    "psxview.not_in_ethread_pool_false_avg": 0.16821104,
    "psxview.not_in_pspcid_list_false_avg": 0.126158281,
    "psxview.not_in_csrss_handles_false_avg": 0.277441256,
    "psxview.not_in_session_false_avg": 0.180773388,
    "psxview.not_in_deskthrd_false_avg": 0.332056363,
    "modules.nmodules": 138.0,
    "svcscan.nservices": 395.0,
    "svcscan.kernel_drivers": 222.0,
    "svcscan.fs_drivers": 26.0,
    "svcscan.process_services": 27.0,
    "svcscan.shared_process_services": 118.0,
    "svcscan.interactive_process_services": 0.0,
    "svcscan.nactive": 124.0,
    "callbacks.ncallbacks": 88.0,
    "callbacks.nanonymous": 0.0,
    "callbacks.ngeneric": 8.0,
    "Class": 0.0,
    "sample_id": 13406.0
}