{
    "Category": 0.0,
    "pslist.nproc": 57.0,
    "pslist.nppid": 20.0,
    "pslist.avg_threads": 11.61557531,
    "pslist.nprocs64bit": 0.0,
    "pslist.avg_handlers": 253.2161052,
    "dlllist.ndlls": 2640.0,
    "dlllist.avg_dlls_per_proc": 45.81727631,
    "handles.nhandles": 14591.0,
    "handles.avg_handles_per_proc": 256.6033437,
    "handles.nport": 0.0,
    "handles.nfile": 1163.0,
    "handles.nevent": 4867.0,
    "handles.ndesktop": 62.0,
    "handles.nkey": 1198.0,
    "handles.nthread": 1399.0,
    "handles.ndirectory": 135.0,
    "handles.nsemaphore": 866.0,
    "handles.ntimer": 174.0,
    "handles.nsection": 493.0,
    "handles.nmutant": 507.0,
    "ldrmodules.not_in_load": 109.0,
    "ldrmodules.not_in_init": 163.0,
    "ldrmodules.not_in_mem": 109.0,
    "ldrmodules.not_in_load_avg": 0.041503469,
    "ldrmodules.not_in_init_avg": 0.061901455,
    "ldrmodules.not_in_mem_avg": 0.041503469,
    "malfind.ninjections": 13.0,
    "malfind.commitCharge": 48.0,
    "malfind.protection": 80.0,
    "malfind.uniqueInjections": 1.363637103,
    "psxview.not_in_pslist": 2.0,
    "psxview.not_in_eprocess_pool": 0.0,
    "psxview.not_in_ethread_pool": 3.0,
    "psxview.not_in_pspcid_list": 2.0,
    "psxview.not_in_csrss_handles": 7.0,
    "psxview.not_in_session": 4.0,
    "psxview.not_in_deskthrd": 10.0,
    "psxview.not_in_pslist_false_avg": 0.047502614,
    "psxview.not_in_eprocess_pool_false_avg": 0.0,
    "psxview.not_in_ethread_pool_false_avg": 0.059989545,
    "psxview.not_in_pspcid_list_false_avg": 0.047502614,
    "psxview.not_in_csrss_handles_false_avg": 0.126101238,
    "psxview.not_in_session_false_avg": 0.080558459,
    "psxview.not_in_deskthrd_false_avg": 0.175685006,
    "modules.nmodules": 138.0,
    "svcscan.nservices": 392.0,
    "svcscan.kernel_drivers": 222.0,
    "svcscan.fs_drivers": 26.0,
    "svcscan.process_services": 24.0,
    "svcscan.shared_process_services": 118.0,
    "svcscan.interactive_process_services": 0.0,
    "svcscan.nactive": 128.0,
    "callbacks.ncallbacks": 87.0,
    "callbacks.nanonymous": 0.0,
    "callbacks.ngeneric": 8.0,
    "Class": 0.0,
    "sample_id": 28615.0
}