{
    "Category": 2.0,
    "pslist.nproc": 43.0,
    "pslist.nppid": 17.0,
    "pslist.avg_threads": 9.627906977,
    "pslist.nprocs64bit": 0.0,
    "pslist.avg_handlers": 203.2325581,
    "dlllist.ndlls": 1660.0,
    "dlllist.avg_dlls_per_proc": 38.60465116,
    "handles.nhandles": 8740.0,
    "handles.avg_handles_per_proc": 208.0952381,
    "handles.nport": 0.0,
    "handles.nfile": 652.0,
    "handles.nevent": 3002.0,
    "handles.ndesktop": 45.0,
    "handles.nkey": 751.0,
    "handles.nthread": 744.0,
    "handles.ndirectory": 106.0,
    "handles.nsemaphore": 646.0,
    "handles.ntimer": 129.0,
    "handles.nsection": 196.0,
    "handles.nmutant": 271.0,
    "ldrmodules.not_in_load": 45.0,
    "ldrmodules.not_in_init": 86.0,
    "ldrmodules.not_in_mem": 45.0,
    "ldrmodules.not_in_load_avg": 0.026533019,
    "ldrmodules.not_in_init_avg": 0.050707547,
    "ldrmodules.not_in_mem_avg": 0.026533019,
    "malfind.ninjections": 3.0,
    "malfind.commitCharge": 3.0,
    "malfind.protection": 18.0,
    "malfind.uniqueInjections": 1.0,
    "psxview.not_in_pslist": 1.0,
    "psxview.not_in_eprocess_pool": 0.0,
    "psxview.not_in_ethread_pool": 2.0,
    "psxview.not_in_pspcid_list": 1.0,
    "psxview.not_in_csrss_handles": 6.0,
    "psxview.not_in_session": 3.0,
    "psxview.not_in_deskthrd": 8.0,
    "psxview.not_in_pslist_false_avg": 0.022727273,
    "psxview.not_in_eprocess_pool_false_avg": 0.0,
    "psxview.not_in_ethread_pool_false_avg": 0.045454545,
    "psxview.not_in_pspcid_list_false_avg": 0.022727273,
    "psxview.not_in_csrss_handles_false_avg": 0.136363636,
    "psxview.not_in_session_false_avg": 0.068181818,
    "psxview.not_in_deskthrd_false_avg": 0.181818182,
    "modules.nmodules": 138.0,
    "svcscan.nservices": 389.0,
    "svcscan.kernel_drivers": 221.0,
    "svcscan.fs_drivers": 26.0,
    "svcscan.process_services": 24.0,
    "svcscan.shared_process_services": 116.0,
    "svcscan.interactive_process_services": 0.0,
    "svcscan.nactive": 124.0,
    "callbacks.ncallbacks": 86.0,
    "callbacks.nanonymous": 0.0,
    "callbacks.ngeneric": 8.0,
    "Class": 1.0,
    "sample_id": 29692.0
}