{
    "Category": 0.0,
    "pslist.nproc": 43.0,
    "pslist.nppid": 17.0,
    "pslist.avg_threads": 11.33839182,
    "pslist.nprocs64bit": 0.0,
    "pslist.avg_handlers": 267.5232482,
    "dlllist.ndlls": 2012.0,
    "dlllist.avg_dlls_per_proc": 46.07712768,
    "handles.nhandles": 11687.0,
    "handles.avg_handles_per_proc": 271.8019596,
    "handles.nport": 0.0,
    "handles.nfile": 912.0,
    "handles.nevent": 3986.0,
    "handles.ndesktop": 48.0,
    "handles.nkey": 1011.0,
    "handles.nthread": 979.0,
    "handles.ndirectory": 107.0,
    "handles.nsemaphore": 775.0,
    "handles.ntimer": 139.0,
    "handles.nsection": 378.0,
    "handles.nmutant": 418.0,
    "ldrmodules.not_in_load": 89.0,
    "ldrmodules.not_in_init": 130.0,
    "ldrmodules.not_in_mem": 89.0,
    "ldrmodules.not_in_load_avg": 0.043504797,
    "ldrmodules.not_in_init_avg": 0.063626361,
    "ldrmodules.not_in_mem_avg": 0.043504797,
    "malfind.ninjections": 7.0,
    "malfind.commitCharge": 9.0,
    "malfind.protection": 45.0,
    "malfind.uniqueInjections": 1.431027334,
    "psxview.not_in_pslist": 9.0,
    "psxview.not_in_eprocess_pool": 0.0,
    "psxview.not_in_ethread_pool": 9.0,
    "psxview.not_in_pspcid_list": 9.0,
    "psxview.not_in_csrss_handles": 13.0,
    "psxview.not_in_session": 11.0,
    "psxview.not_in_deskthrd": 15.0,
    "psxview.not_in_pslist_false_avg": 0.170265472,
    "psxview.not_in_eprocess_pool_false_avg": 0.0,
    "psxview.not_in_ethread_pool_false_avg": 0.182805957,
    "psxview.not_in_pspcid_list_false_avg": 0.170265472,
    "psxview.not_in_csrss_handles_false_avg": 0.258824007,
    "psxview.not_in_session_false_avg": 0.208274497,
    "psxview.not_in_deskthrd_false_avg": 0.296833032,
    "modules.nmodules": 138.0,
    "svcscan.nservices": 392.0,
    "svcscan.kernel_drivers": 222.0,
    "svcscan.fs_drivers": 26.0,
    "svcscan.process_services": 24.0,
    "svcscan.shared_process_services": 118.0,
    "svcscan.interactive_process_services": 0.0,
    "svcscan.nactive": 125.0,
    "callbacks.ncallbacks": 87.0,
    "callbacks.nanonymous": 0.0,
    "callbacks.ngeneric": 8.0,
    "Class": 0.0,
    "sample_id": 3136.0
}