{
    "Category": 0.0,
    "pslist.nproc": 45.0,
    "pslist.nppid": 17.0,
    "pslist.avg_threads": 10.34916409,
    "pslist.nprocs64bit": 0.0,
    "pslist.avg_handlers": 242.5773347,
    "dlllist.ndlls": 1979.0,
    "dlllist.avg_dlls_per_proc": 43.14202334,
    "handles.nhandles": 11132.0,
    "handles.avg_handles_per_proc": 248.0039581,
    "handles.nport": 0.0,
    "handles.nfile": 835.0,
    "handles.nevent": 3864.0,
    "handles.ndesktop": 51.0,
    "handles.nkey": 932.0,
    "handles.nthread": 912.0,
    "handles.ndirectory": 111.0,
    "handles.nsemaphore": 750.0,
    "handles.ntimer": 146.0,
    "handles.nsection": 340.0,
    "handles.nmutant": 363.0,
    "ldrmodules.not_in_load": 85.0,
    "ldrmodules.not_in_init": 128.0,
    "ldrmodules.not_in_mem": 85.0,
    "ldrmodules.not_in_load_avg": 0.042510039,
    "ldrmodules.not_in_init_avg": 0.063901392,
    "ldrmodules.not_in_mem_avg": 0.042510039,
    "malfind.ninjections": 5.0,
    "malfind.commitCharge": 6.0,
    "malfind.protection": 35.0,
    "malfind.uniqueInjections": 1.205508887,
    "psxview.not_in_pslist": 4.0,
    "psxview.not_in_eprocess_pool": 0.0,
    "psxview.not_in_ethread_pool": 5.0,
    "psxview.not_in_pspcid_list": 4.0,
    "psxview.not_in_csrss_handles": 9.0,
    "psxview.not_in_session": 6.0,
    "psxview.not_in_deskthrd": 11.0,
    "psxview.not_in_pslist_false_avg": 0.091925891,
    "psxview.not_in_eprocess_pool_false_avg": 0.0,
    "psxview.not_in_ethread_pool_false_avg": 0.111717594,
    "psxview.not_in_pspcid_list_false_avg": 0.091925891,
    "psxview.not_in_csrss_handles_false_avg": 0.190884403,
    "psxview.not_in_session_false_avg": 0.131509296,
    "psxview.not_in_deskthrd_false_avg": 0.230467809,
    "modules.nmodules": 138.0,
    "svcscan.nservices": 392.0,
    "svcscan.kernel_drivers": 222.0,
    "svcscan.fs_drivers": 26.0,
    "svcscan.process_services": 24.0,
    "svcscan.shared_process_services": 118.0,
    "svcscan.interactive_process_services": 0.0,
    "svcscan.nactive": 127.0,
    "callbacks.ncallbacks": 87.0,
    "callbacks.nanonymous": 0.0,
    "callbacks.ngeneric": 8.0,
    "Class": 0.0,
    "sample_id": 13219.0
}