{
    "Category": 0.0,
    "pslist.nproc": 49.0,
    "pslist.nppid": 18.0,
    "pslist.avg_threads": 12.50654125,
    "pslist.nprocs64bit": 0.0,
    "pslist.avg_handlers": 302.316314,
    "dlllist.ndlls": 2605.0,
    "dlllist.avg_dlls_per_proc": 52.25847506,
    "handles.nhandles": 15067.0,
    "handles.avg_handles_per_proc": 302.316314,
    "handles.nport": 0.0,
    "handles.nfile": 1104.0,
    "handles.nevent": 5067.0,
    "handles.ndesktop": 53.0,
    "handles.nkey": 1478.0,
    "handles.nthread": 1285.0,
    "handles.ndirectory": 119.0,
    "handles.nsemaphore": 1004.0,
    "handles.ntimer": 162.0,
    "handles.nsection": 491.0,
    "handles.nmutant": 550.0,
    "ldrmodules.not_in_load": 133.0,
    "ldrmodules.not_in_init": 182.0,
    "ldrmodules.not_in_mem": 133.0,
    "ldrmodules.not_in_load_avg": 0.049451006,
    "ldrmodules.not_in_init_avg": 0.067555376,
    "ldrmodules.not_in_mem_avg": 0.049451006,
    "malfind.ninjections": 19.0,
    "malfind.commitCharge": 85.0,
    "malfind.protection": 115.0,
    "malfind.uniqueInjections": 1.778776918,
    "psxview.not_in_pslist": 0.0,
    "psxview.not_in_eprocess_pool": 0.0,
    "psxview.not_in_ethread_pool": 0.0,
    "psxview.not_in_pspcid_list": 0.0,
    "psxview.not_in_csrss_handles": 4.0,
    "psxview.not_in_session": 2.0,
    "psxview.not_in_deskthrd": 5.0,
    "psxview.not_in_pslist_false_avg": 0.0,
    "psxview.not_in_eprocess_pool_false_avg": 0.0,
    "psxview.not_in_ethread_pool_false_avg": 0.0,
    "psxview.not_in_pspcid_list_false_avg": 0.0,
    "psxview.not_in_csrss_handles_false_avg": 0.080273832,
    "psxview.not_in_session_false_avg": 0.040136916,
    "psxview.not_in_deskthrd_false_avg": 0.108665067,
    "modules.nmodules": 138.0,
    "svcscan.nservices": 392.0,
    "svcscan.kernel_drivers": 222.0,
    "svcscan.fs_drivers": 26.0,
    "svcscan.process_services": 24.0,
    "svcscan.shared_process_services": 118.0,
    "svcscan.interactive_process_services": 0.0,
    "svcscan.nactive": 124.0,
    "callbacks.ncallbacks": 87.0,
    "callbacks.nanonymous": 0.0,
    "callbacks.ngeneric": 8.0,
    "Class": 0.0,
    "sample_id": 3785.0
}