{
    "Category": 4.0,
    "pslist.nproc": 48.0,
    "pslist.nppid": 20.0,
    "pslist.avg_threads": 8.979166667,
    "pslist.nprocs64bit": 0.0,
    "pslist.avg_handlers": 182.0208333,
    "dlllist.ndlls": 1658.0,
    "dlllist.avg_dlls_per_proc": 34.54166667,
    "handles.nhandles": 8739.0,
    "handles.avg_handles_per_proc": 189.9782609,
    "handles.nport": 0.0,
    "handles.nfile": 650.0,
    "handles.nevent": 3015.0,
    "handles.ndesktop": 49.0,
    "handles.nkey": 706.0,
    "handles.nthread": 806.0,
    "handles.ndirectory": 109.0,
    "handles.nsemaphore": 662.0,
    "handles.ntimer": 120.0,
    "handles.nsection": 181.0,
    "handles.nmutant": 263.0,
    "ldrmodules.not_in_load": 47.0,
    "ldrmodules.not_in_init": 92.0,
    "ldrmodules.not_in_mem": 47.0,
    "ldrmodules.not_in_load_avg": 0.027614571,
    "ldrmodules.not_in_init_avg": 0.054054054,
    "ldrmodules.not_in_mem_avg": 0.027614571,
    "malfind.ninjections": 29.0,
    "malfind.commitCharge": 1740.0,
    "malfind.protection": 174.0,
    "malfind.uniqueInjections": 3.625,
    "psxview.not_in_pslist": 6.0,
    "psxview.not_in_eprocess_pool": 0.0,
    "psxview.not_in_ethread_pool": 8.0,
    "psxview.not_in_pspcid_list": 6.0,
    "psxview.not_in_csrss_handles": 12.0,
    "psxview.not_in_session": 8.0,
    "psxview.not_in_deskthrd": 14.0,
    "psxview.not_in_pslist_false_avg": 0.111111111,
    "psxview.not_in_eprocess_pool_false_avg": 0.0,
    "psxview.not_in_ethread_pool_false_avg": 0.148148148,
    "psxview.not_in_pspcid_list_false_avg": 0.111111111,
    "psxview.not_in_csrss_handles_false_avg": 0.222222222,
    "psxview.not_in_session_false_avg": 0.148148148,
    "psxview.not_in_deskthrd_false_avg": 0.259259259,
    "modules.nmodules": 138.0,
    "svcscan.nservices": 389.0,
    "svcscan.kernel_drivers": 221.0,
    "svcscan.fs_drivers": 26.0,
    "svcscan.process_services": 24.0,
    "svcscan.shared_process_services": 116.0,
    "svcscan.interactive_process_services": 0.0,
    "svcscan.nactive": 122.0,
    "callbacks.ncallbacks": 86.0,
    "callbacks.nanonymous": 0.0,
    "callbacks.ngeneric": 8.0,
    "Class": 1.0,
    "sample_id": 35392.0
}