{
    "Category": 3.0,
    "pslist.nproc": 33.0,
    "pslist.nppid": 13.0,
    "pslist.avg_threads": 10.54545455,
    "pslist.nprocs64bit": 0.0,
    "pslist.avg_handlers": 188.8181818,
    "dlllist.ndlls": 1236.0,
    "dlllist.avg_dlls_per_proc": 37.45454545,
    "handles.nhandles": 6231.0,
    "handles.avg_handles_per_proc": 188.8181818,
    "handles.nport": 0.0,
    "handles.nfile": 561.0,
    "handles.nevent": 2014.0,
    "handles.ndesktop": 34.0,
    "handles.nkey": 454.0,
    "handles.nthread": 562.0,
    "handles.ndirectory": 83.0,
    "handles.nsemaphore": 447.0,
    "handles.ntimer": 97.0,
    "handles.nsection": 90.0,
    "handles.nmutant": 185.0,
    "ldrmodules.not_in_load": 40.0,
    "ldrmodules.not_in_init": 74.0,
    "ldrmodules.not_in_mem": 40.0,
    "ldrmodules.not_in_load_avg": 0.031372549,
    "ldrmodules.not_in_init_avg": 0.058039216,
    "ldrmodules.not_in_mem_avg": 0.031372549,
    "malfind.ninjections": 2.0,
    "malfind.commitCharge": 2.0,
    "malfind.protection": 12.0,
    "malfind.uniqueInjections": 1.0,
    "psxview.not_in_pslist": 0.0,
    "psxview.not_in_eprocess_pool": 0.0,
    "psxview.not_in_ethread_pool": 0.0,
    "psxview.not_in_pspcid_list": 0.0,
    "psxview.not_in_csrss_handles": 4.0,
    "psxview.not_in_session": 2.0,
    "psxview.not_in_deskthrd": 6.0,
    "psxview.not_in_pslist_false_avg": 0.0,
    "psxview.not_in_eprocess_pool_false_avg": 0.0,
    "psxview.not_in_ethread_pool_false_avg": 0.0,
    "psxview.not_in_pspcid_list_false_avg": 0.0,
    "psxview.not_in_csrss_handles_false_avg": 0.121212121,
    "psxview.not_in_session_false_avg": 0.060606061,
    "psxview.not_in_deskthrd_false_avg": 0.181818182,
    "modules.nmodules": 138.0,
    "svcscan.nservices": 387.0,
    "svcscan.kernel_drivers": 221.0,
    "svcscan.fs_drivers": 26.0,
    "svcscan.process_services": 23.0,
    "svcscan.shared_process_services": 115.0,
    "svcscan.interactive_process_services": 0.0,
    "svcscan.nactive": 114.0,
    "callbacks.ncallbacks": 88.0,
    "callbacks.nanonymous": 0.0,
    "callbacks.ngeneric": 8.0,
    "Class": 1.0,
    "sample_id": 32263.0
}