{
    "Category": 0.0,
    "pslist.nproc": 43.0,
    "pslist.nppid": 17.0,
    "pslist.avg_threads": 10.92494042,
    "pslist.nprocs64bit": 0.0,
    "pslist.avg_handlers": 258.5905508,
    "dlllist.ndlls": 1940.0,
    "dlllist.avg_dlls_per_proc": 44.38920808,
    "handles.nhandles": 11303.0,
    "handles.avg_handles_per_proc": 264.6696503,
    "handles.nport": 0.0,
    "handles.nfile": 866.0,
    "handles.nevent": 3902.0,
    "handles.ndesktop": 48.0,
    "handles.nkey": 987.0,
    "handles.nthread": 934.0,
    "handles.ndirectory": 107.0,
    "handles.nsemaphore": 751.0,
    "handles.ntimer": 137.0,
    "handles.nsection": 361.0,
    "handles.nmutant": 373.0,
    "ldrmodules.not_in_load": 81.0,
    "ldrmodules.not_in_init": 122.0,
    "ldrmodules.not_in_mem": 81.0,
    "ldrmodules.not_in_load_avg": 0.041542425,
    "ldrmodules.not_in_init_avg": 0.062207001,
    "ldrmodules.not_in_mem_avg": 0.041542425,
    "malfind.ninjections": 5.0,
    "malfind.commitCharge": 7.0,
    "malfind.protection": 34.0,
    "malfind.uniqueInjections": 1.428146885,
    "psxview.not_in_pslist": 10.0,
    "psxview.not_in_eprocess_pool": 0.0,
    "psxview.not_in_ethread_pool": 11.0,
    "psxview.not_in_pspcid_list": 10.0,
    "psxview.not_in_csrss_handles": 15.0,
    "psxview.not_in_session": 12.0,
    "psxview.not_in_deskthrd": 17.0,
    "psxview.not_in_pslist_false_avg": 0.186189421,
    "psxview.not_in_eprocess_pool_false_avg": 0.0,
    "psxview.not_in_ethread_pool_false_avg": 0.204808364,
    "psxview.not_in_pspcid_list_false_avg": 0.186189421,
    "psxview.not_in_csrss_handles_false_avg": 0.279284133,
    "psxview.not_in_session_false_avg": 0.223427306,
    "psxview.not_in_deskthrd_false_avg": 0.316522017,
    "modules.nmodules": 138.0,
    "svcscan.nservices": 392.0,
    "svcscan.kernel_drivers": 222.0,
    "svcscan.fs_drivers": 26.0,
    "svcscan.process_services": 24.0,
    "svcscan.shared_process_services": 118.0,
    "svcscan.interactive_process_services": 0.0,
    "svcscan.nactive": 126.0,
    "callbacks.ncallbacks": 87.0,
    "callbacks.nanonymous": 0.0,
    "callbacks.ngeneric": 8.0,
    "Class": 0.0,
    "sample_id": 6618.0
}