{
    "Category": 0.0,
    "pslist.nproc": 38.0,
    "pslist.nppid": 12.0,
    "pslist.avg_threads": 13.77708042,
    "pslist.nprocs64bit": 0.0,
    "pslist.avg_handlers": 291.4818203,
    "dlllist.ndlls": 1908.0,
    "dlllist.avg_dlls_per_proc": 49.67592017,
    "handles.nhandles": 11190.0,
    "handles.avg_handles_per_proc": 291.4818203,
    "handles.nport": 0.0,
    "handles.nfile": 953.0,
    "handles.nevent": 3952.0,
    "handles.ndesktop": 42.0,
    "handles.nkey": 782.0,
    "handles.nthread": 1133.0,
    "handles.ndirectory": 96.0,
    "handles.nsemaphore": 717.0,
    "handles.ntimer": 135.0,
    "handles.nsection": 340.0,
    "handles.nmutant": 327.0,
    "ldrmodules.not_in_load": 64.0,
    "ldrmodules.not_in_init": 99.0,
    "ldrmodules.not_in_mem": 64.0,
    "ldrmodules.not_in_load_avg": 0.03397062,
    "ldrmodules.not_in_init_avg": 0.052608166,
    "ldrmodules.not_in_mem_avg": 0.03397062,
    "malfind.ninjections": 3.0,
    "malfind.commitCharge": 4.0,
    "malfind.protection": 22.0,
    "malfind.uniqueInjections": 1.381881069,
    "psxview.not_in_pslist": 0.0,
    "psxview.not_in_eprocess_pool": 0.0,
    "psxview.not_in_ethread_pool": 0.0,
    "psxview.not_in_pspcid_list": 0.0,
    "psxview.not_in_csrss_handles": 4.0,
    "psxview.not_in_session": 2.0,
    "psxview.not_in_deskthrd": 6.0,
    "psxview.not_in_pslist_false_avg": 0.007665432,
    "psxview.not_in_eprocess_pool_false_avg": 0.0,
    "psxview.not_in_ethread_pool_false_avg": 0.007665432,
    "psxview.not_in_pspcid_list_false_avg": 0.007665432,
    "psxview.not_in_csrss_handles_false_avg": 0.111015733,
    "psxview.not_in_session_false_avg": 0.059340582,
    "psxview.not_in_deskthrd_false_avg": 0.162690883,
    "modules.nmodules": 138.0,
    "svcscan.nservices": 395.0,
    "svcscan.kernel_drivers": 222.0,
    "svcscan.fs_drivers": 26.0,
    "svcscan.process_services": 27.0,
    "svcscan.shared_process_services": 118.0,
    "svcscan.interactive_process_services": 0.0,
    "svcscan.nactive": 124.0,
    "callbacks.ncallbacks": 88.0,
    "callbacks.nanonymous": 0.0,
    "callbacks.ngeneric": 8.0,
    "Class": 0.0,
    "sample_id": 8828.0
}