{
    "Category": 0.0,
    "pslist.nproc": 32.0,
    "pslist.nppid": 12.0,
    "pslist.avg_threads": 12.28860538,
    "pslist.nprocs64bit": 0.0,
    "pslist.avg_handlers": 282.4614084,
    "dlllist.ndlls": 1524.0,
    "dlllist.avg_dlls_per_proc": 47.63173667,
    "handles.nhandles": 9040.0,
    "handles.avg_handles_per_proc": 301.3588357,
    "handles.nport": 0.0,
    "handles.nfile": 691.0,
    "handles.nevent": 3112.0,
    "handles.ndesktop": 33.0,
    "handles.nkey": 757.0,
    "handles.nthread": 756.0,
    "handles.ndirectory": 81.0,
    "handles.nsemaphore": 643.0,
    "handles.ntimer": 123.0,
    "handles.nsection": 214.0,
    "handles.nmutant": 299.0,
    "ldrmodules.not_in_load": 51.0,
    "ldrmodules.not_in_init": 79.0,
    "ldrmodules.not_in_mem": 51.0,
    "ldrmodules.not_in_load_avg": 0.034158835,
    "ldrmodules.not_in_init_avg": 0.052522185,
    "ldrmodules.not_in_mem_avg": 0.034158835,
    "malfind.ninjections": 3.0,
    "malfind.commitCharge": 4.0,
    "malfind.protection": 18.0,
    "malfind.uniqueInjections": 1.5,
    "psxview.not_in_pslist": 3.0,
    "psxview.not_in_eprocess_pool": 0.0,
    "psxview.not_in_ethread_pool": 5.0,
    "psxview.not_in_pspcid_list": 3.0,
    "psxview.not_in_csrss_handles": 9.0,
    "psxview.not_in_session": 5.0,
    "psxview.not_in_deskthrd": 11.0,
    "psxview.not_in_pslist_false_avg": 0.092497968,
    "psxview.not_in_eprocess_pool_false_avg": 0.0,
    "psxview.not_in_ethread_pool_false_avg": 0.149216845,
    "psxview.not_in_pspcid_list_false_avg": 0.092497968,
    "psxview.not_in_csrss_handles_false_avg": 0.262654599,
    "psxview.not_in_session_false_avg": 0.149216845,
    "psxview.not_in_deskthrd_false_avg": 0.319373476,
    "modules.nmodules": 138.0,
    "svcscan.nservices": 395.0,
    "svcscan.kernel_drivers": 222.0,
    "svcscan.fs_drivers": 26.0,
    "svcscan.process_services": 27.0,
    "svcscan.shared_process_services": 118.0,
    "svcscan.interactive_process_services": 0.0,
    "svcscan.nactive": 123.0,
    "callbacks.ncallbacks": 88.0,
    "callbacks.nanonymous": 0.0,
    "callbacks.ngeneric": 8.0,
    "Class": 0.0,
    "sample_id": 14111.0
}