{
    "Category": 0.0,
    "pslist.nproc": 45.0,
    "pslist.nppid": 17.0,
    "pslist.avg_threads": 10.90662538,
    "pslist.nprocs64bit": 0.0,
    "pslist.avg_handlers": 262.6578031,
    "dlllist.ndlls": 2111.0,
    "dlllist.avg_dlls_per_proc": 46.16595813,
    "handles.nhandles": 12014.0,
    "handles.avg_handles_per_proc": 262.6578031,
    "handles.nport": 0.0,
    "handles.nfile": 903.0,
    "handles.nevent": 4119.0,
    "handles.ndesktop": 49.0,
    "handles.nkey": 1139.0,
    "handles.nthread": 977.0,
    "handles.ndirectory": 110.0,
    "handles.nsemaphore": 824.0,
    "handles.ntimer": 146.0,
    "handles.nsection": 361.0,
    "handles.nmutant": 421.0,
    "ldrmodules.not_in_load": 87.0,
    "ldrmodules.not_in_init": 132.0,
    "ldrmodules.not_in_mem": 87.0,
    "ldrmodules.not_in_load_avg": 0.040358359,
    "ldrmodules.not_in_init_avg": 0.060918497,
    "ldrmodules.not_in_mem_avg": 0.040358359,
    "malfind.ninjections": 11.0,
    "malfind.commitCharge": 75.0,
    "malfind.protection": 71.0,
    "malfind.uniqueInjections": 1.723991385,
    "psxview.not_in_pslist": 1.0,
    "psxview.not_in_eprocess_pool": 0.0,
    "psxview.not_in_ethread_pool": 1.0,
    "psxview.not_in_pspcid_list": 1.0,
    "psxview.not_in_csrss_handles": 5.0,
    "psxview.not_in_session": 3.0,
    "psxview.not_in_deskthrd": 6.0,
    "psxview.not_in_pslist_false_avg": 0.024858985,
    "psxview.not_in_eprocess_pool_false_avg": 0.0,
    "psxview.not_in_ethread_pool_false_avg": 0.024858985,
    "psxview.not_in_pspcid_list_false_avg": 0.024858985,
    "psxview.not_in_csrss_handles_false_avg": 0.110116206,
    "psxview.not_in_session_false_avg": 0.067487595,
    "psxview.not_in_deskthrd_false_avg": 0.13320285,
    "modules.nmodules": 138.0,
    "svcscan.nservices": 392.0,
    "svcscan.kernel_drivers": 222.0,
    "svcscan.fs_drivers": 26.0,
    "svcscan.process_services": 24.0,
    "svcscan.shared_process_services": 118.0,
    "svcscan.interactive_process_services": 0.0,
    "svcscan.nactive": 123.0,
    "callbacks.ncallbacks": 87.0,
    "callbacks.nanonymous": 0.0,
    "callbacks.ngeneric": 8.0,
    "Class": 0.0,
    "sample_id": 19075.0
}