{
    "Category": 0.0,
    "pslist.nproc": 40.0,
    "pslist.nppid": 16.0,
    "pslist.avg_threads": 10.74975379,
    "pslist.nprocs64bit": 0.0,
    "pslist.avg_handlers": 251.0339663,
    "dlllist.ndlls": 1741.0,
    "dlllist.avg_dlls_per_proc": 43.31498173,
    "handles.nhandles": 10094.0,
    "handles.avg_handles_per_proc": 256.8257735,
    "handles.nport": 0.0,
    "handles.nfile": 794.0,
    "handles.nevent": 3503.0,
    "handles.ndesktop": 44.0,
    "handles.nkey": 841.0,
    "handles.nthread": 825.0,
    "handles.ndirectory": 99.0,
    "handles.nsemaphore": 703.0,
    "handles.ntimer": 127.0,
    "handles.nsection": 296.0,
    "handles.nmutant": 319.0,
    "ldrmodules.not_in_load": 71.0,
    "ldrmodules.not_in_init": 108.0,
    "ldrmodules.not_in_mem": 71.0,
    "ldrmodules.not_in_load_avg": 0.040644516,
    "ldrmodules.not_in_init_avg": 0.061951743,
    "ldrmodules.not_in_mem_avg": 0.040644516,
    "malfind.ninjections": 3.0,
    "malfind.commitCharge": 4.0,
    "malfind.protection": 18.0,
    "malfind.uniqueInjections": 1.481855857,
    "psxview.not_in_pslist": 9.0,
    "psxview.not_in_eprocess_pool": 0.0,
    "psxview.not_in_ethread_pool": 10.0,
    "psxview.not_in_pspcid_list": 9.0,
    "psxview.not_in_csrss_handles": 14.0,
    "psxview.not_in_session": 11.0,
    "psxview.not_in_deskthrd": 15.0,
    "psxview.not_in_pslist_false_avg": 0.183175431,
    "psxview.not_in_eprocess_pool_false_avg": 0.0,
    "psxview.not_in_ethread_pool_false_avg": 0.200998134,
    "psxview.not_in_pspcid_list_false_avg": 0.183175431,
    "psxview.not_in_csrss_handles_false_avg": 0.282185751,
    "psxview.not_in_session_false_avg": 0.22376924,
    "psxview.not_in_deskthrd_false_avg": 0.320305358,
    "modules.nmodules": 138.0,
    "svcscan.nservices": 392.0,
    "svcscan.kernel_drivers": 222.0,
    "svcscan.fs_drivers": 26.0,
    "svcscan.process_services": 24.0,
    "svcscan.shared_process_services": 118.0,
    "svcscan.interactive_process_services": 0.0,
    "svcscan.nactive": 126.0,
    "callbacks.ncallbacks": 87.0,
    "callbacks.nanonymous": 0.0,
    "callbacks.ngeneric": 8.0,
    "Class": 0.0,
    "sample_id": 27869.0
}