{
    "Category": 3.0,
    "pslist.nproc": 116.0,
    "pslist.nppid": 17.0,
    "pslist.avg_threads": 3.344827586,
    "pslist.nprocs64bit": 0.0,
    "pslist.avg_handlers": 73.92241379,
    "dlllist.ndlls": 1629.0,
    "dlllist.avg_dlls_per_proc": 14.04310345,
    "handles.nhandles": 8651.0,
    "handles.avg_handles_per_proc": 216.275,
    "handles.nport": 0.0,
    "handles.nfile": 955.0,
    "handles.nevent": 2909.0,
    "handles.ndesktop": 42.0,
    "handles.nkey": 702.0,
    "handles.nthread": 708.0,
    "handles.ndirectory": 102.0,
    "handles.nsemaphore": 615.0,
    "handles.ntimer": 116.0,
    "handles.nsection": 169.0,
    "handles.nmutant": 254.0,
    "ldrmodules.not_in_load": 47.0,
    "ldrmodules.not_in_init": 86.0,
    "ldrmodules.not_in_mem": 47.0,
    "ldrmodules.not_in_load_avg": 0.029746835,
    "ldrmodules.not_in_init_avg": 0.05443038,
    "ldrmodules.not_in_mem_avg": 0.029746835,
    "malfind.ninjections": 9.0,
    "malfind.commitCharge": 89.0,
    "malfind.protection": 54.0,
    "malfind.uniqueInjections": 3.0,
    "psxview.not_in_pslist": 3.0,
    "psxview.not_in_eprocess_pool": 0.0,
    "psxview.not_in_ethread_pool": 79.0,
    "psxview.not_in_pspcid_list": 3.0,
    "psxview.not_in_csrss_handles": 83.0,
    "psxview.not_in_session": 5.0,
    "psxview.not_in_deskthrd": 85.0,
    "psxview.not_in_pslist_false_avg": 0.025210084,
    "psxview.not_in_eprocess_pool_false_avg": 0.0,
    "psxview.not_in_ethread_pool_false_avg": 0.663865546,
    "psxview.not_in_pspcid_list_false_avg": 0.025210084,
    "psxview.not_in_csrss_handles_false_avg": 0.697478992,
    "psxview.not_in_session_false_avg": 0.042016807,
    "psxview.not_in_deskthrd_false_avg": 0.714285714,
    "modules.nmodules": 138.0,
    "svcscan.nservices": 389.0,
    "svcscan.kernel_drivers": 221.0,
    "svcscan.fs_drivers": 26.0,
    "svcscan.process_services": 24.0,
    "svcscan.shared_process_services": 116.0,
    "svcscan.interactive_process_services": 0.0,
    "svcscan.nactive": 119.0,
    "callbacks.ncallbacks": 86.0,
    "callbacks.nanonymous": 0.0,
    "callbacks.ngeneric": 8.0,
    "Class": 1.0,
    "sample_id": 31872.0
}